VicPy/__init__.py
VicPy/VicPy.cp313-win_amd64.pyd
vicpy-1.6.0.dist-info/METADATA
vicpy-1.6.0.dist-info/WHEEL
vicpy-1.6.0.dist-info/licenses/LICENSE
vicpy-1.6.0.dist-info/RECORD
