Metadata-Version: 2.2
Name: VicPy
Version: 1.6.0
Summary: The VicPy module from Correlated Solutions
License: Copyright (C) 2025 Correlated Solutions, Inc. 
Classifier: Programming Language :: Python :: 3
Classifier: Programming Language :: Python :: Implementation :: CPython
Classifier: Operating System :: Unix
Classifier: Operating System :: Microsoft :: Windows
Classifier: Topic :: Software Development
Classifier: Topic :: Scientific/Engineering
Project-URL: homepage, https://correlated.kayako.com/article/55-installing-vicpy
Project-URL: documentation, https://correlated.kayako.com/article/55-installing-vicpy
Requires-Python: >=3.10
Requires-Dist: numpy
